odoo10_addon_sale_procurement_group_by_requested_date_sale_sourced_by_line-10.0.1.0.0.99.dev6-py3.6-nspkg.pth
odoo/addons/sale_procurement_group_by_requested_date_sale_sourced_by_line/README.rst
odoo/addons/sale_procurement_group_by_requested_date_sale_sourced_by_line/__init__.py
odoo/addons/sale_procurement_group_by_requested_date_sale_sourced_by_line/__manifest__.py
odoo/addons/sale_procurement_group_by_requested_date_sale_sourced_by_line/i18n/ca.po
odoo/addons/sale_procurement_group_by_requested_date_sale_sourced_by_line/i18n/es.po
odoo/addons/sale_procurement_group_by_requested_date_sale_sourced_by_line/i18n/sale_procurement_group_by_requested_date_sale_sourced_by_line.pot
odoo/addons/sale_procurement_group_by_requested_date_sale_sourced_by_line/models/__init__.py
odoo/addons/sale_procurement_group_by_requested_date_sale_sourced_by_line/models/sale_order.py
odoo/addons/sale_procurement_group_by_requested_date_sale_sourced_by_line/static/description/icon.png
odoo/addons/sale_procurement_group_by_requested_date_sale_sourced_by_line/tests/__init__.py
odoo/addons/sale_procurement_group_by_requested_date_sale_sourced_by_line/tests/test_sale.py
odoo10_addon_sale_procurement_group_by_requested_date_sale_sourced_by_line-10.0.1.0.0.99.dev6.dist-info/METADATA
odoo10_addon_sale_procurement_group_by_requested_date_sale_sourced_by_line-10.0.1.0.0.99.dev6.dist-info/WHEEL
odoo10_addon_sale_procurement_group_by_requested_date_sale_sourced_by_line-10.0.1.0.0.99.dev6.dist-info/namespace_packages.txt
odoo10_addon_sale_procurement_group_by_requested_date_sale_sourced_by_line-10.0.1.0.0.99.dev6.dist-info/top_level.txt
odoo10_addon_sale_procurement_group_by_requested_date_sale_sourced_by_line-10.0.1.0.0.99.dev6.dist-info/RECORD
