Metadata-Version: 2.1
Name: odoo10-addon-sale-procurement-group-by-requested-date-sale-sourced-by-line
Version: 10.0.1.0.0.99.dev6
Summary: Integrates sale_source_by_line and sale procurement group
Home-page: https://github.com/OCA/sale-workflow
Author: Eficent , Odoo Community Association (OCA)
Author-email: support@odoo-community.org
License: AGPL-3
Platform: UNKNOWN
Classifier: Programming Language :: Python
Classifier: Framework :: Odoo
Classifier: License :: OSI Approved :: GNU Affero General Public License v3
Requires-Python: ~=2.7
Requires-Dist: odoo10-addon-sale-procurement-group-by-requested-date
Requires-Dist: odoo10-addon-sale-sourced-by-line
Requires-Dist: odoo (<10.1dev,>=10.0)
